monzoh/__init__.py
monzoh/async_client.py
monzoh/auth.py
monzoh/client.py
monzoh/exceptions.py
monzoh/py.typed
monzoh/utils.py
monzoh/webhooks.py
monzoh/api/__init__.py
monzoh/api/accounts.py
monzoh/api/async_accounts.py
monzoh/api/async_attachments.py
monzoh/api/async_feed.py
monzoh/api/async_pots.py
monzoh/api/async_receipts.py
monzoh/api/async_transactions.py
monzoh/api/async_webhooks.py
monzoh/api/attachments.py
monzoh/api/feed.py
monzoh/api/pots.py
monzoh/api/receipts.py
monzoh/api/transactions.py
monzoh/api/webhooks.py
monzoh/cli/__init__.py
monzoh/cli/auth_flow.py
monzoh/cli/credentials.py
monzoh/cli/oauth_server.py
monzoh/cli/token_cache.py
monzoh/core/__init__.py
monzoh/core/async_base.py
monzoh/core/base.py
monzoh/core/mock_data.py
monzoh/models/__init__.py
monzoh/models/accounts.py
monzoh/models/attachments.py
monzoh/models/base.py
monzoh/models/feed.py
monzoh/models/pots.py
monzoh/models/receipts.py
monzoh/models/transactions.py
monzoh/models/webhooks.py
monzoh-1.2.0.dist-info/METADATA
monzoh-1.2.0.dist-info/WHEEL
monzoh-1.2.0.dist-info/entry_points.txt
monzoh-1.2.0.dist-info/licenses/LICENSE
monzoh-1.2.0.dist-info/RECORD
